openrtdynamics2/ORTDtoNumpy.py
openrtdynamics2/__init__.py
openrtdynamics2/code_generation_helper.py
openrtdynamics2/dsp.py
openrtdynamics2/manifest_import.py
openrtdynamics2/py_execute.py
openrtdynamics2/targets.py
openrtdynamics2/lang/__init__.py
openrtdynamics2/lang/block_interface.py
openrtdynamics2/lang/block_prototypes.py
openrtdynamics2/lang/block_prototypes_single_subsystem.py
openrtdynamics2/lang/block_prototypes_subsystems.py
openrtdynamics2/lang/block_prototypes_switched_subsystems.py
openrtdynamics2/lang/circular_buffer.py
openrtdynamics2/lang/code_generation_templates.py
openrtdynamics2/lang/core_blocks.py
openrtdynamics2/lang/high_level_user_commands.py
openrtdynamics2/lang/lang.py
openrtdynamics2/lang/libraries.py
openrtdynamics2/lang/signal_interface.py
openrtdynamics2/lang/standard_library.py
openrtdynamics2/lang/subsystems.py
openrtdynamics2/lang/system_context.py
openrtdynamics2/lang/diagram_core/__init__.py
openrtdynamics2/lang/diagram_core/code_build_commands.py
openrtdynamics2/lang/diagram_core/code_generation_helper.py
openrtdynamics2/lang/diagram_core/datatype_propagation.py
openrtdynamics2/lang/diagram_core/diagram_compiler.py
openrtdynamics2/lang/diagram_core/graph_traversion.py
openrtdynamics2/lang/diagram_core/irpar.py
openrtdynamics2/lang/diagram_core/system.py
openrtdynamics2/lang/diagram_core/system_manifest.py
openrtdynamics2/lang/diagram_core/datatypes/__init__.py
openrtdynamics2/lang/diagram_core/datatypes/datatypes.py
openrtdynamics2/lang/diagram_core/signal_network/Block.py
openrtdynamics2/lang/diagram_core/signal_network/__init__.py
openrtdynamics2/lang/diagram_core/signal_network/signals.py
openrtdynamics2-0.4.3.dist-info/LICENSE
openrtdynamics2-0.4.3.dist-info/METADATA
openrtdynamics2-0.4.3.dist-info/WHEEL
openrtdynamics2-0.4.3.dist-info/top_level.txt
openrtdynamics2-0.4.3.dist-info/RECORD
