Metadata-Version: 2.1
Name: openrtdynamics2
Version: 0.4.3
Summary: OpenRTDynamics 2
Home-page: https://openrtdynamics.github.io/
Author: Christian Klauer
Author-email: chr@gmail.com
License: UNKNOWN
Platform: UNKNOWN
Classifier: Programming Language :: Python :: 3
Classifier: License :: OSI Approved :: MIT License
Classifier: Operating System :: OS Independent
Requires-Python: >=3.6
Requires-Dist: numpy
Requires-Dist: control
Requires-Dist: colorama
Requires-Dist: prettytable
Requires-Dist: cppyy
Requires-Dist: pygments
